skyshelve/__init__.py
skyshelve/libskyshelve.h
skyshelve/libskyshelve.so
skyshelve-0.2.1.dist-info/licenses/LICENSE
skyshelve-0.2.1.dist-info/METADATA
skyshelve-0.2.1.dist-info/WHEEL
skyshelve-0.2.1.dist-info/top_level.txt
skyshelve-0.2.1.dist-info/RECORD
